webhoseio/__init__.py
webhoseio-0.3.dist-info/DESCRIPTION.rst
webhoseio-0.3.dist-info/METADATA
webhoseio-0.3.dist-info/RECORD
webhoseio-0.3.dist-info/WHEEL
webhoseio-0.3.dist-info/metadata.json
webhoseio-0.3.dist-info/top_level.txt
