Metadata-Version: 2.0
Name: webhoseio
Version: 0.3
Summary: Simple client library for the webhose.io REST API
Home-page: https://github.com/Webhose/webhoseio-python
Author: Ran Geva
Author-email: ran@webhose.io
License: MIT
Platform: UNKNOWN
Classifier: Development Status :: 4 - Beta
Classifier: Intended Audience :: Developers
Classifier: Natural Language :: English
Classifier: License :: OSI Approved :: MIT License
Classifier: Programming Language :: Python
Classifier: Programming Language :: Python :: 2.6
Classifier: Programming Language :: Python :: 2.7
Classifier: Programming Language :: Python :: 3
Classifier: Programming Language :: Python :: 3.3
Classifier: Programming Language :: Python :: 3.4
Requires-Dist: requests (>=2.0.0)
